onnxoptimizer/__init__.py
onnxoptimizer/__main__.py
onnxoptimizer/cpp2py_export.cc
onnxoptimizer/model_util.cc
onnxoptimizer/model_util.h
onnxoptimizer/onnx_opt_cpp2py_export.cpython-310-x86_64-linux-gnu.so
onnxoptimizer/onnxoptimizer_main.py
onnxoptimizer/optimize.cc
onnxoptimizer/optimize.h
onnxoptimizer/pass.cc
onnxoptimizer/pass.h
onnxoptimizer/pass_manager.cc
onnxoptimizer/pass_manager.h
onnxoptimizer/pass_registry.cc
onnxoptimizer/pass_registry.h
onnxoptimizer/version.py
onnxoptimizer/c_api/onnxoptimizer_c_api.cc
onnxoptimizer/c_api/onnxoptimizer_c_api.h
onnxoptimizer/passes/adjust_add.h
onnxoptimizer/passes/adjust_slice_and_matmul.h
onnxoptimizer/passes/bitscast.h
onnxoptimizer/passes/cse_util.h
onnxoptimizer/passes/data_type.h
onnxoptimizer/passes/eliminate_common_subexpression.h
onnxoptimizer/passes/eliminate_consecutive_idempotent_ops.h
onnxoptimizer/passes/eliminate_deadend.h
onnxoptimizer/passes/eliminate_duplicate_initializer.h
onnxoptimizer/passes/eliminate_identity.h
onnxoptimizer/passes/eliminate_if_with_const_cond.h
onnxoptimizer/passes/eliminate_nop_cast.h
onnxoptimizer/passes/eliminate_nop_concat.h
onnxoptimizer/passes/eliminate_nop_dropout.h
onnxoptimizer/passes/eliminate_nop_expand.h
onnxoptimizer/passes/eliminate_nop_flatten.h
onnxoptimizer/passes/eliminate_nop_monotone_argmax.h
onnxoptimizer/passes/eliminate_nop_pad.h
onnxoptimizer/passes/eliminate_nop_reshape.h
onnxoptimizer/passes/eliminate_nop_split.h
onnxoptimizer/passes/eliminate_nop_transpose.h
onnxoptimizer/passes/eliminate_nop_with_unit.h
onnxoptimizer/passes/eliminate_shape_gather.h
onnxoptimizer/passes/eliminate_shape_op.h
onnxoptimizer/passes/eliminate_slice_after_shape.h
onnxoptimizer/passes/eliminate_unused_initializer.h
onnxoptimizer/passes/extract_constant_to_initializer.h
onnxoptimizer/passes/fuse_add_bias_into_conv.h
onnxoptimizer/passes/fuse_bn_into_conv.h
onnxoptimizer/passes/fuse_concat_into_reshape.h
onnxoptimizer-0.4.2.dist-info/METADATA
onnxoptimizer-0.4.2.dist-info/WHEEL
onnxoptimizer-0.4.2.dist-info/entry_points.txt
onnxoptimizer-0.4.2.dist-info/top_level.txt
onnxoptimizer-0.4.2.dist-info/RECORD
onnxoptimizer-0.4.2.dist-info/licenses/LICENSE
