Metadata-Version: 2.4
Name: onnxoptimizer
Version: 0.4.2
Summary: ONNX Optimizer
Author-email: ONNX Optimizer Authors <onnx-technical-discuss@lists.lfai.foundation>
License-Expression: Apache-2.0
Project-URL: Homepage, https://github.com/onnx/optimizer
Keywords: deep-learning,ONNX
Requires-Python: >=3.10
License-File: LICENSE
Requires-Dist: onnx
Dynamic: license-file
